{
  "name": "ggestructure:roguelike_room",
  "fallback": "minecraft:empty",
  "elements": [
    {
      "weight": 4,
      "element": {
        "element_type": "minecraft:single_pool_element",
        "location": "ggestructure:roguelike_room_cross_1",
        "projection": "rigid",
        "processors": "minecraft:empty"
      }
    },
    {
      "weight": 5,
      "element": {
        "element_type": "minecraft:single_pool_element",
        "location": "ggestructure:roguelike_room_cross_spawner_1",
        "projection": "rigid",
        "processors": "minecraft:empty"
      }
    },
    {
      "weight": 1,
      "element": {
        "element_type": "minecraft:single_pool_element",
        "location": "ggestructure:roguelike_fall_large_1",
        "projection": "rigid",
        "processors": "minecraft:empty"
      }
    },
    {
      "weight": 1,
      "element": {
        "element_type": "minecraft:single_pool_element",
        "location": "ggestructure:roguelike_fall_medium_1",
        "projection": "rigid",
        "processors": "minecraft:empty"
      }
    },
    {
      "weight": 1,
      "element": {
        "element_type": "minecraft:single_pool_element",
        "location": "ggestructure:roguelike_fall_small_1",
        "projection": "rigid",
        "processors": "minecraft:empty"
      }
    },
    {
      "weight": 2,
      "element": {
        "element_type": "minecraft:single_pool_element",
        "location": "ggestructure:roguelike_room_peaceful_1",
        "projection": "rigid",
        "processors": "minecraft:empty"
      }
    },
    {
      "weight": 8,
      "element": {
        "element_type": "minecraft:single_pool_element",
        "location": "ggestructure:roguelike_room_regular_1",
        "projection": "rigid",
        "processors": "minecraft:empty"
      }
    },
    {
      "weight": 6,
      "element": {
        "element_type": "minecraft:single_pool_element",
        "location": "ggestructure:roguelike_room_regular_chests_1",
        "projection": "rigid",
        "processors": "minecraft:empty"
      }
    },
    {
      "weight": 3,
      "element": {
        "element_type": "minecraft:single_pool_element",
        "location": "ggestructure:roguelike_room_regular_chests_rare_1",
        "projection": "rigid",
        "processors": "minecraft:empty"
      }
    },
    {
      "weight": 8,
      "element": {
        "element_type": "minecraft:single_pool_element",
        "location": "ggestructure:roguelike_stairs_1",
        "projection": "rigid",
        "processors": "minecraft:empty"
      }
    },
    {
      "weight": 2,
      "element": {
        "element_type": "minecraft:single_pool_element",
        "location": "ggestructure:roguelike_room_stop_1",
        "projection": "rigid",
        "processors": "minecraft:empty"
      }
    },
    {
      "weight": 5,
      "element": {
        "element_type": "minecraft:single_pool_element",
        "location": "ggestructure:roguelike_room_t_1",
        "projection": "rigid",
        "processors": "minecraft:empty"
      }
    },
    {
      "weight": 3,
      "element": {
        "element_type": "minecraft:single_pool_element",
        "location": "ggestructure:roguelike_room_t_spawner_1",
        "projection": "rigid",
        "processors": "minecraft:empty"
      }
    },
    {
      "weight": 2,
      "element": {
        "element_type": "minecraft:single_pool_element",
        "location": "ggestructure:roguelike_room_t_spawner_chest_1",
        "projection": "rigid",
        "processors": "minecraft:empty"
      }
    },
    {
      "weight": 3,
      "element": {
        "element_type": "minecraft:single_pool_element",
        "location": "ggestructure:roguelike_room_magma_1",
        "projection": "rigid",
        "processors": "minecraft:empty"
      }
    },
    {
      "weight": 3,
      "element": {
        "element_type": "minecraft:single_pool_element",
        "location": "ggestructure:roguelike_room_magma_hard_1",
        "projection": "rigid",
        "processors": "minecraft:empty"
      }
    },
    {
      "weight": 2,
      "element": {
        "element_type": "minecraft:single_pool_element",
        "location": "ggestructure:roguelike_room_magma_hard_chests_1",
        "projection": "rigid",
        "processors": "minecraft:empty"
      }
    },
    {
      "weight": 1,
      "element": {
        "element_type": "minecraft:single_pool_element",
        "location": "ggestructure:roguelike_room_treasure_1",
        "projection": "rigid",
        "processors": "minecraft:empty"
      }
    },
    {
      "weight": 1,
      "element": {
        "element_type": "minecraft:single_pool_element",
        "location": "ggestructure:roguelike_room_treasure_coal_1",
        "projection": "rigid",
        "processors": "minecraft:empty"
      }
    },
    {
      "weight": 1,
      "element": {
        "element_type": "minecraft:single_pool_element",
        "location": "ggestructure:roguelike_room_treasure_coal_spawners_1",
        "projection": "rigid",
        "processors": "minecraft:empty"
      }
    },
    {
      "weight": 1,
      "element": {
        "element_type": "minecraft:single_pool_element",
        "location": "ggestructure:roguelike_room_treasure_diamond_1",
        "projection": "rigid",
        "processors": "minecraft:empty"
      }
    },
    {
      "weight": 1,
      "element": {
        "element_type": "minecraft:single_pool_element",
        "location": "ggestructure:roguelike_room_treasure_diamond_spawners_1",
        "projection": "rigid",
        "processors": "minecraft:empty"
      }
    },
    {
      "weight": 4,
      "element": {
        "element_type": "minecraft:single_pool_element",
        "location": "ggestructure:roguelike_room_cavern_1",
        "projection": "rigid",
        "processors": "minecraft:empty"
      }
    },
    {
      "weight": 2,
      "element": {
        "element_type": "minecraft:single_pool_element",
        "location": "ggestructure:roguelike_room_cavern_dripstone_1",
        "projection": "rigid",
        "processors": "minecraft:empty"
      }
    },
    {
      "weight": 3,
      "element": {
        "element_type": "minecraft:single_pool_element",
        "location": "ggestructure:roguelike_room_cavern_dripstone_spawner_1",
        "projection": "rigid",
        "processors": "minecraft:empty"
      }
    },
    {
      "weight": 1,
      "element": {
        "element_type": "minecraft:single_pool_element",
        "location": "ggestructure:roguelike_room_cavern_mineral_1",
        "projection": "rigid",
        "processors": "minecraft:empty"
      }
    },
    {
      "weight": 2,
      "element": {
        "element_type": "minecraft:single_pool_element",
        "location": "ggestructure:roguelike_room_cavern_mineral_spawner_1",
        "projection": "rigid",
        "processors": "minecraft:empty"
      }
    },
    {
      "weight": 3,
      "element": {
        "element_type": "minecraft:single_pool_element",
        "location": "ggestructure:roguelike_room_cavern_spawner_1",
        "projection": "rigid",
        "processors": "minecraft:empty"
      }
    },
    {
      "weight": 2,
      "element": {
        "element_type": "minecraft:single_pool_element",
        "location": "ggestructure:roguelike_room_cavern_spawner_hard_1",
        "projection": "rigid",
        "processors": "minecraft:empty"
      }
    },
    {
      "weight": 5,
      "element": {
        "element_type": "minecraft:single_pool_element",
        "location": "ggestructure:roguelike_room_dripstone_1",
        "projection": "rigid",
        "processors": "minecraft:empty"
      }
    },
    {
      "weight": 1,
      "element": {
        "element_type": "minecraft:single_pool_element",
        "location": "ggestructure:roguelike_room_dripstone_chests_1",
        "projection": "rigid",
        "processors": "minecraft:empty"
      }
    },
    {
      "weight": 5,
      "element": {
        "element_type": "minecraft:single_pool_element",
        "location": "ggestructure:roguelike_room_peaceful_dripstone_1",
        "projection": "rigid",
        "processors": "minecraft:empty"
      }
    },
    {
      "weight": 5,
      "element": {
        "element_type": "minecraft:single_pool_element",
        "location": "ggestructure:roguelike_room_spawners_dripstone_1",
        "projection": "rigid",
        "processors": "minecraft:empty"
      }
    },
    {
      "weight": 3,
      "element": {
        "element_type": "minecraft:single_pool_element",
        "location": "ggestructure:roguelike_room_spawners_dripstone_chests_1",
        "projection": "rigid",
        "processors": "minecraft:empty"
      }
    },
    {
      "weight": 3,
      "element": {
        "element_type": "minecraft:single_pool_element",
        "location": "ggestructure:roguelike_room_spider_infested_web_1",
        "projection": "rigid",
        "processors": "minecraft:empty"
      }
    },
    {
      "weight": 2,
      "element": {
        "element_type": "minecraft:single_pool_element",
        "location": "ggestructure:roguelike_room_treasure_diamond_spawners_1",
        "projection": "rigid",
        "processors": "minecraft:empty"
      }
    },
    {
      "weight": 3,
      "element": {
        "element_type": "minecraft:single_pool_element",
        "location": "ggestructure:roguelike_room_spider_infested_web_chests_1",
        "projection": "rigid",
        "processors": "minecraft:empty"
      }
    },
    {
      "weight": 2,
      "element": {
        "element_type": "minecraft:single_pool_element",
        "location": "ggestructure:roguelike_room_spider_infested_webless_1",
        "projection": "rigid",
        "processors": "minecraft:empty"
      }
    },
    {
      "weight": 3,
      "element": {
        "element_type": "minecraft:single_pool_element",
        "location": "ggestructure:roguelike_room_spider_infested_webless_chests_1",
        "projection": "rigid",
        "processors": "minecraft:empty"
      }
    },
    {
      "weight": 4,
      "element": {
        "element_type": "minecraft:single_pool_element",
        "location": "ggestructure:roguelike_room_spider_web_1",
        "projection": "rigid",
        "processors": "minecraft:empty"
      }
    },
    {
      "weight": 2,
      "element": {
        "element_type": "minecraft:single_pool_element",
        "location": "ggestructure:roguelike_room_spider_web_chests_1",
        "projection": "rigid",
        "processors": "minecraft:empty"
      }
    },
    {
      "weight": 2,
      "element": {
        "element_type": "minecraft:single_pool_element",
        "location": "ggestructure:roguelike_room_spider_webless_1",
        "projection": "rigid",
        "processors": "minecraft:empty"
      }
    },
    {
      "weight": 2,
      "element": {
        "element_type": "minecraft:single_pool_element",
        "location": "ggestructure:roguelike_room_spider_webless_chests_1",
        "projection": "rigid",
        "processors": "minecraft:empty"
      }
    },
    {
      "weight": 2,
      "element": {
        "element_type": "minecraft:single_pool_element",
        "location": "ggestructure:roguelike_room_fall_large_1",
        "projection": "rigid",
        "processors": "minecraft:empty"
      }
    },
    {
      "weight": 2,
      "element": {
        "element_type": "minecraft:single_pool_element",
        "location": "ggestructure:roguelike_room_fall_medium_1",
        "projection": "rigid",
        "processors": "minecraft:empty"
      }
    },
    {
      "weight": 2,
      "element": {
        "element_type": "minecraft:single_pool_element",
        "location": "ggestructure:roguelike_room_fall_small_1",
        "projection": "rigid",
        "processors": "minecraft:empty"
      }
    }
  ]
}
